COPYING
HACKING
MANIFEST.in
NEWS
README
dh_splitpackage.1
setup.cfg
setup.py
dh_splitpackage/__init__.py
dh_splitpackage/__main__.py
dh_splitpackage/test.py
dh_splitpackage.egg-info/PKG-INFO
dh_splitpackage.egg-info/SOURCES.txt
dh_splitpackage.egg-info/dependency_links.txt
dh_splitpackage.egg-info/entry_points.txt
dh_splitpackage.egg-info/requires.txt
dh_splitpackage.egg-info/top_level.txt