Metadata-Version: 1.0
Name: dh-splitpackage
Version: 0.2.2
Summary: dh_split - split monolithic installation directory into sub-packages without pulling your hair out
Home-page: https://launchpad.net/dh_splitpackage
Author: Zygmunt Krynicki
Author-email: zygmunt.krynicki@canonical.com
License: UNKNOWN
Platform: UNKNOWN
Classifier: Development Status :: 4 - Beta
Classifier: Environment :: Console
Classifier: Intended Audience :: Developers
Classifier: License :: OSI Approved :: GNU General Public License (GPL)
Classifier: Operating System :: OS Independent
Classifier: Programming Language :: Python :: 2.6
Classifier: Programming Language :: Python :: 2.7
Classifier: Topic :: Software Development :: Build Tools
Classifier: Topic :: System :: Software Distribution
